texweaver/__init__.py
texweaver/default.yaml
texweaver/entrypoint.py
texweaver/markdown.py
texweaver/tex_config.py
texweaver/tex_parser.py
texweaver-0.3.1.dist-info/LICENSE
texweaver-0.3.1.dist-info/METADATA
texweaver-0.3.1.dist-info/WHEEL
texweaver-0.3.1.dist-info/entry_points.txt
texweaver-0.3.1.dist-info/top_level.txt
texweaver-0.3.1.dist-info/RECORD
